tesla_api/__init__.py
tesla_api/charge.py
tesla_api/climate.py
tesla_api/controls.py
tesla_api/energy.py
tesla_api/vehicle.py
tesla_api-2.0.1.dist-info/LICENSE
tesla_api-2.0.1.dist-info/METADATA
tesla_api-2.0.1.dist-info/WHEEL
tesla_api-2.0.1.dist-info/top_level.txt
tesla_api-2.0.1.dist-info/RECORD
