Metadata-Version: 2.1
Name: tesla-api
Version: 2.0.1
Summary: API client for Tesla
Home-page: https://github.com/mlowijs/tesla_api
Author: M. Lowijs
Author-email: mlowijs@gmail.com
License: UNKNOWN
Platform: UNKNOWN
Classifier: Programming Language :: Python :: 3.7
Classifier: License :: OSI Approved :: MIT License
Classifier: Operating System :: OS Independent
Requires-Dist: aiohttp
